MANIFEST.in
README
README.md
README.rst
setup.py
docs/Cakewalk DevXchange - Specifications - sfz File Format.pdf
docs/xi_specs.txt
samplicity/__init__.py
samplicity/common.py
samplicity/ez_setup.py
samplicity/samplicity.py
samplicity/xi_reader.py
samplicity.egg-info/PKG-INFO
samplicity.egg-info/SOURCES.txt
samplicity.egg-info/dependency_links.txt
samplicity.egg-info/entry_points.txt
samplicity.egg-info/requires.txt
samplicity.egg-info/top_level.txt