Metadata-Version: 1.0
Name: samplicity
Version: 0.5.1
Summary: .SFZ to .XI musical samples format converter
Home-page: https://github.com/ckald/Samplicity
Author: Andii Magalich
Author-email: andrew.magalich@gmail.com
License: UNKNOWN
Platform: UNKNOWN
